LICENSE.txt
MANIFEST.in
README.md
setup.py
bin/quantgo
bin/quantgo_complete
qg_cli/__init__.py
qg_cli/api_schema.py
qg_cli/cli.py
qg_cli/client.py
qg_cli/completer.py
qg_cli/config.py
qg_cli/errors.py
qg_cli/qgclient.py
qg_cli/signatures.py
quantgo_cli.egg-info/PKG-INFO
quantgo_cli.egg-info/SOURCES.txt
quantgo_cli.egg-info/dependency_links.txt
quantgo_cli.egg-info/requires.txt
quantgo_cli.egg-info/top_level.txt