Metadata-Version: 1.1
Name: quantgo-cli
Version: 2.0.1
Summary: QuantGo Command Line Tool.
Home-page: https://quantgo.com
Author: Nikolay Krysiuk
Author-email: nikolay@quantgo.com
License: Copyright (c) 2013 QuantGo
